easylogconfig/__init__.py
easylogconfig-0.2.0.dist-info/LICENSE
easylogconfig-0.2.0.dist-info/METADATA
easylogconfig-0.2.0.dist-info/WHEEL
easylogconfig-0.2.0.dist-info/top_level.txt
easylogconfig-0.2.0.dist-info/RECORD
