Metadata-Version: 2.1
Name: easylogconfig
Version: 0.2.0
Summary: Easy configure logging
Home-page: https://github.com/tierpod/easylogconfig
Author: Pavel Podkorytov
Author-email: pod.pavel@gmail.com
License: MIT
Platform: UNKNOWN
Classifier: Development Status :: 3 - Alpha
Classifier: Programming Language :: Python :: 3
License-File: LICENSE
